bcdd/__init__.py
bcdd/__main__.py
bcdd/color.py
bcdd/crypto.py
bcdd/data.py
bcdd/option.py
bcdd/path.py
bcdd/updater.py
bcdd/files/version.txt
bcdd-1.0.1.dist-info/LICENSE
bcdd-1.0.1.dist-info/METADATA
bcdd-1.0.1.dist-info/WHEEL
bcdd-1.0.1.dist-info/top_level.txt
bcdd-1.0.1.dist-info/RECORD
