Metadata-Version: 2.1
Name: bcdd
Version: 1.0.1
Summary: A tool for decrypting and encrypting battle cats .dat files
Home-page: https://github.com/fieryhenry/bcdd
Author: fieryhenry
Classifier: Programming Language :: Python :: 3
Classifier: License :: OSI Approved :: MIT License
Classifier: Operating System :: OS Independent
Requires-Python: >=3.9
License-File: LICENSE
Requires-Dist: colored
Requires-Dist: pycryptodomex
Requires-Dist: requests
Provides-Extra: testing
Requires-Dist: pytest ; extra == 'testing'
Requires-Dist: pytest-cov ; extra == 'testing'
